kaumena/__init__.py
kaumena/conf/models/mdxnet/bass.yaml
kaumena/conf/models/mdxnet/drums.yaml
kaumena/conf/models/mdxnet/mixer.yaml
kaumena/conf/models/mdxnet/other.yaml
kaumena/conf/models/mdxnet/vocals.yaml
kaumena/conf/models/mdxnet.yaml
kaumena/conf/models/open_unmix.yaml
kaumena/grids/htdemucs.py
kaumena/models/__init__.py
kaumena/models/_htdemucs/README.md
kaumena/models/_htdemucs/__init__.py
kaumena/models/_htdemucs/_demucs.py
kaumena/models/_htdemucs/_hdemucs.py
kaumena/models/_htdemucs/_states.py
kaumena/models/_htdemucs/_transformer.py
kaumena/models/_htdemucs/htdemucs.py
kaumena/models/_mdxnet/README.md
kaumena/models/_mdxnet/__init__.py
kaumena/models/_mdxnet/_modules.py
kaumena/models/_mdxnet/mdxnet.py
kaumena/models/htdemucs.py
kaumena/models/interface.py
kaumena/models/mdxnet.py
kaumena/models/openumnix.py
kaumena/tests/__init__.py
kaumena/tests/conftest.py
kaumena/tests/htdemucs_test.py
kaumena/tests/openunmix_test.py
kaumena/utils/__init__.py
kaumena/utils/audio.py
kaumena/utils/evaluation.py
kaumena/utils/spectro.py
kaumena/utils/testing.py
kaumena/utils/transfrom.py
kaumena/utils/zero_checkpoint_gen.py
kaumena-0.1.0.dist-info/METADATA
kaumena-0.1.0.dist-info/WHEEL
kaumena-0.1.0.dist-info/RECORD
