Metadata-Version: 2.3
Name: kaumena
Version: 0.1.0
Summary: An toolkit for music source separation with pytorch
Author: jabkascript
Requires-Python: >=3.12,<4.0
Classifier: Programming Language :: Python :: 3
Classifier: Programming Language :: Python :: 3.12
Classifier: Programming Language :: Python :: 3.13
Requires-Dist: demucs (==4.0.1)
Requires-Dist: einops (==0.8.1)
Requires-Dist: hydra-core (==1.3.2)
Requires-Dist: librosa (==0.11.0)
Requires-Dist: numpy (==2.2.4)
Requires-Dist: omegaconf (==2.3.0)
Requires-Dist: openunmix (==1.3.0)
Requires-Dist: pytorch-lightning (==2.5.1.post0)
Requires-Dist: torchaudio (==2.7.0)
Requires-Dist: xformers (==0.0.30)
